LICENSE
MANIFEST.in
README.rst
setup.py
bottle_streamline.egg-info/PKG-INFO
bottle_streamline.egg-info/SOURCES.txt
bottle_streamline.egg-info/dependency_links.txt
bottle_streamline.egg-info/requires.txt
bottle_streamline.egg-info/top_level.txt
streamline/__init__.py
streamline/base.py
streamline/forms.py
streamline/template.py
streamline/utils.py