Metadata-Version: 1.1
Name: bottle-streamline
Version: 1.0.post2
Summary: Python module writing class-based route handlers in bottle.
Home-page: https://github.com/Outernet-Project/bottle-streamline
Author: Outernet Inc
Author-email: apps@outernet.is
License: BSD
Keywords: bottle route class
Platform: UNKNOWN
Classifier: Development Status :: 5 - Production/Stable
Classifier: License :: OSI Approved :: BSD License
Classifier: Programming Language :: Python :: 2.7
Classifier: Programming Language :: Python :: 3
Classifier: Topic :: Utilities
